servefastai/__init__.py
servefastai/static/css/.DS_Store
servefastai/static/css/bootstrap-grid.css
servefastai/static/css/bootstrap-grid.css.map
servefastai/static/css/bootstrap-grid.min.css
servefastai/static/css/bootstrap-grid.min.css.map
servefastai/static/css/bootstrap-reboot.css
servefastai/static/css/bootstrap-reboot.css.map
servefastai/static/css/bootstrap-reboot.min.css
servefastai/static/css/bootstrap-reboot.min.css.map
servefastai/static/css/bootstrap.css
servefastai/static/css/bootstrap.css.map
servefastai/static/css/bootstrap.min.css
servefastai/static/css/bootstrap.min.css.map
servefastai/static/js/bootstrap.bundle.js
servefastai/static/js/bootstrap.bundle.js.map
servefastai/static/js/bootstrap.bundle.min.js
servefastai/static/js/bootstrap.bundle.min.js.map
servefastai/static/js/bootstrap.js
servefastai/static/js/bootstrap.js.map
servefastai/static/js/bootstrap.min.js
servefastai/static/js/bootstrap.min.js.map
servefastai/static/js/jquery-3.3.1.slim.min.js
servefastai/static/js/popper.min.js
servefastai/templates/predict.html
servefastai/templates/upload.html
servefastai-0.1.4.dist-info/METADATA
servefastai-0.1.4.dist-info/RECORD
servefastai-0.1.4.dist-info/WHEEL
servefastai-0.1.4.dist-info/top_level.txt
