Metadata-Version: 2.1
Name: servefastai
Version: 0.1.4
Summary: Serve FastAI and get a Web UI with one line of code
Home-page: https://github.com/aakashns/servefastai
Author: Aakash N S
Author-email: opensource@swiftace.ai
License: UNKNOWN
Platform: UNKNOWN
Classifier: Programming Language :: Python :: 3
Classifier: License :: OSI Approved :: MIT License
Classifier: Operating System :: OS Independent
Requires-Dist: flask
